pivotal_tools
