Metadata-Version: 1.0
Name: pivotal-tools
Version: 0.14
Summary: Collection of pivotal command line tools
Home-page: http://github.com/jtushman/pivotal_tools
Author: Jonathan Tushman
Author-email: jonathan.tushman@zefr.com
License: MIT
Platform: UNKNOWN
